{
  "title":"Device Orientation events",
  "description":"API for detecting orientation and motion events from the device running the browser.",
  "spec":"http://www.w3.org/TR/orientation-event/",
  "status":"wd",
  "links":[
    {
      "url":"http://www.html5rocks.com/en/tutorials/device/orientation/",
      "title":"HTML5 Rocks tutorial"
    }
  ],
  "bugs":[
    
  ],
  "categories":[
    "JS API"
  ],
  "stats":{
    "ie":{
      "5.5":"n",
      "6":"n",
      "7":"n",
      "8":"n",
      "9":"n",
      "10":"n",
      "11":"u"
    },
    "firefox":{
      "2":"n",
      "3":"n",
      "3.5":"n",
      "3.6":"a",
      "4":"a",
      "5":"a",
      "6":"a",
      "7":"a",
      "8":"a",
      "9":"a",
      "10":"a",
      "11":"a",
      "12":"a",
      "13":"a",
      "14":"a",
      "15":"a",
      "16":"a",
      "17":"a",
      "18":"a"
    },
    "chrome":{
      "4":"n",
      "5":"n",
      "6":"n",
      "7":"y",
      "8":"y",
      "9":"y",
      "10":"y",
      "11":"y",
      "12":"y",
      "13":"y",
      "14":"y",
      "15":"y",
      "16":"y",
      "17":"y",
      "18":"y",
      "19":"y",
      "20":"y",
      "21":"y",
      "22":"y",
      "23":"y",
      "24":"y",
      "25":"y"
    },
    "safari":{
      "3.1":"n",
      "3.2":"n",
      "4":"n",
      "5":"n",
      "5.1":"n",
      "6":"n"
    },
    "opera":{
      "9":"n",
      "9.5-9.6":"n",
      "10.0-10.1":"n",
      "10.5":"n",
      "10.6":"n",
      "11":"n",
      "11.1":"n",
      "11.5":"n",
      "11.6":"n",
      "12":"n",
      "12.1":"n",
      "12.5":"n"
    },
    "ios_saf":{
      "3.2":"n",
      "4.0-4.1":"n",
      "4.2-4.3":"y",
      "5.0-5.1":"y",
      "6":"y"
    },
    "op_mini":{
      "5.0-7.0":"n"
    },
    "android":{
      "2.1":"n",
      "2.2":"n",
      "2.3":"n",
      "3":"y",
      "4":"y",
      "4.1":"y"
    },
    "bb":{
      "7":"n",
      "10":"y"
    },
    "op_mob":{
      "10":"n",
      "11":"n",
      "11.1":"n",
      "11.5":"n",
      "12":"y",
      "12.1":"y"
    },
    "and_chr":{
      "0":"y"
    },
    "and_ff":{
      "0":"y"
    }
  },
  "notes":"Firefox 3.6, 4 and 5 support the non-standard <a href=\\\"https://developer.mozilla.org/en/DOM/MozOrientation\\\">MozOrientation</a> event. Firefox 6+ claims support, but does not appear to work where Chrome does (tested on macbook pro).",
  "usage_perc_y":36.92,
  "usage_perc_a":19.21,
  "ucprefix":false,
  "parent":"",
  "keywords":"",
  "shown":true
}